{
 "fetched_at": "2026-07-19T04:13:00.410807+00:00",
 "items": [
  {
   "title": "من \"جزيرة الشيطان\" إلى ملاذ للفقمات النادرة، كيف غيّرت الطبيعة وجه جزيرة يونانية؟",
   "link": "https://www.bbc.com/arabic/articles/clyl4n352v8o?at_medium=RSS&at_campaign=rss",
   "source": "BBC عربي",
   "time": "2026-07-19T04:00:26+00:00"
  },
  {
   "title": "واشنطن تنهي ضربات \"عقابية\" على إيران لليلة الثامنة، وطهران ترد بهجوم \"واسع\" على مواقع أمريكية في الكويت",
   "link": "https://www.bbc.com/arabic/articles/cwymlr92y93o?at_medium=RSS&at_campaign=rss",
   "source": "BBC عربي",
   "time": "2026-07-19T04:00:24+00:00"
  },
  {
   "title": "Best England team for a long time? That's a fact, says Rice",
   "link": "https://www.bbc.co.uk/sport/football/articles/c4g34gjmyl7o?at_medium=RSS&at_campaign=rss",
   "source": "BBC Sport",
   "time": "2026-07-19T02:29:00+00:00"
  },
  {
   "title": "England beat France in 10-goal thriller to win third-place play-off",
   "link": "https://www.bbc.co.uk/sport/football/videos/cm2gn7v4jljo?at_medium=RSS&at_campaign=rss",
   "source": "BBC Sport",
   "time": "2026-07-19T01:12:34+00:00"
  },
  {
   "title": "Bellingham breaks England World Cup goals record",
   "link": "https://www.bbc.co.uk/sport/football/articles/c0qvzqlp4pdo?at_medium=RSS&at_campaign=rss",
   "source": "BBC Sport",
   "time": "2026-07-19T00:47:11+00:00"
  },
  {
   "title": "England's best World Cup for 60 years - but how should it be judged?",
   "link": "https://www.bbc.co.uk/sport/football/articles/c78g1p05025o?at_medium=RSS&at_campaign=rss",
   "source": "BBC Sport",
   "time": "2026-07-19T00:23:05+00:00"
  },
  {
   "title": "Hat-trick hero Saka: I'm fit and wanted to play more",
   "link": "https://www.skysports.com/football/news/12040/13564841/france-4-6-england-bukayo-saka-reveals-he-is-fully-fit-and-wanted-to-play-more-at-the-world-cup-after-hat-trick-in-third-place-play-off",
   "source": "Sky Sports",
   "time": "2026-07-19T00:16:00+00:00"
  },
  {
   "title": "Golden Boot race: Mbappe pulls two clear of Messi",
   "link": "https://www.skysports.com/football/news/12040/13564837/world-cup-2026-golden-boot-race-kylian-mbappe-pulls-two-goals-clear-of-lionel-messi-ahead-of-world-cup-final",
   "source": "Sky Sports",
   "time": "2026-07-19T00:16:00+00:00"
  },
  {
   "title": "England claim third at World Cup with win in 10-goal thriller over France",
   "link": "https://www.skysports.com/football/france-vs-england/report/549868",
   "source": "Sky Sports",
   "time": "2026-07-19T00:15:00+00:00"
  },
  {
   "title": "Brilliant first half, turbulent second - Tuchel",
   "link": "https://www.bbc.co.uk/sport/football/videos/c1j1djgkg98o?at_medium=RSS&at_campaign=rss",
   "source": "BBC Sport",
   "time": "2026-07-19T00:13:13+00:00"
  },
  {
   "title": "كأس العالم: إنجلترا تحرز الميدالية البرونزية للمرة الأولى بعد فوز كبير على فرنسا 6-4",
   "link": "https://www.bbc.com/arabic/articles/cvgj3glnpjlo?at_medium=RSS&at_campaign=rss",
   "source": "BBC عربي",
   "time": "2026-07-19T00:01:55+00:00"
  },
  {
   "title": "Over to you, Messi - Mbappe leads Golden Boot race for the ages",
   "link": "https://www.bbc.co.uk/sport/football/articles/c89nl42dnpyo?at_medium=RSS&at_campaign=rss",
   "source": "BBC Sport",
   "time": "2026-07-18T23:48:40+00:00"
  },
  {
   "title": "How did England players rate during the World Cup?",
   "link": "https://www.bbc.co.uk/sport/football/articles/cx2jljx84rwo?at_medium=RSS&at_campaign=rss",
   "source": "BBC Sport",
   "time": "2026-07-18T23:31:46+00:00"
  },
  {
   "title": "Saka hat-trick seals 6-4 England win over France in epic World Cup third-place playoff",
   "link": "https://www.theguardian.com/football/2026/jul/19/england-france-world-cup-third-place-playoff-match-report",
   "source": "The Guardian",
   "time": "2026-07-18T23:05:21+00:00"
  },
  {
   "title": "Littler: People can moan about me and Humphries - someone needs to stop us",
   "link": "https://www.skysports.com/darts/news/12040/13564699/luke-littler-ready-to-defend-world-matchplay-title-people-can-moan-about-me-and-luke-humphries-but-someone-needs-to-stop-us",
   "source": "Sky Sports",
   "time": "2026-07-18T23:00:00+00:00"
  }
 ]
}